{"attributes":[],"baby_trigger_for":null,"category":{"name":"plot-advancement","url":"/ic/22/"},"cost":0,"effect_entries":[{"effect":"Used by trainer outside of battle\n:   Opens doors in the goldenrod city Radio Tower.","language":{"name":"en","url":"/lang/9/"},"short_effect":"HS: Opens doors in the Radio Tower. Gen III: Unlocks Silph Co Doors."}],"flavor_text_entries":[{"language":{"name":"zh-Hans","url":"/lang/12/"},"text":"用来打开电台卷帘门的\n卡片式钥匙。","version_group":{"name":"sun-moon","url":"/vg/17/"}},{"language":{"name":"ja","url":"/lang/11/"},"text":"ラジオ局の　シャッターを　開ける\nカード式の　カギ。\n","version_group":{"name":"sun-moon","url":"/vg/17/"}},{"language":{"name":"en","url":"/lang/9/"},"text":"A card key that opens a shutter in the\nRadio Tower.","version_group":{"name":"sun-moon","url":"/vg/17/"}},{"language":{"name":"it","url":"/lang/8/"},"text":"Chiave a scheda che apre le porte automatizzate\ndella Torre Radio.","version_group":{"name":"sun-moon","url":"/vg/17/"}},{"language":{"name":"es","url":"/lang/7/"},"text":"Llave con forma de tarjeta que abre las puertas\nde la Torre Radio.","version_group":{"name":"sun-moon","url":"/vg/17/"}},{"language":{"name":"de","url":"/lang/6/"},"text":"Eine Schlüsselkarte, die eine Tür im Radioturm\nöffnet.","version_group":{"name":"sun-moon","url":"/vg/17/"}},{"language":{"name":"fr","url":"/lang/5/"},"text":"Une clé en forme de carte permettant d’ouvrir\nles cloisons de la Tour Radio.","version_group":{"name":"sun-moon","url":"/vg/17/"}},{"language":{"name":"zh-Hant","url":"/lang/4/"},"text":"用來打開電臺鐵捲門的\n卡片式鑰匙。","version_group":{"name":"sun-moon","url":"/vg/17/"}},{"language":{"name":"ko","url":"/lang/3/"},"text":"라디오방송국의 셔터를 여는\n카드식 열쇠.","version_group":{"name":"sun-moon","url":"/vg/17/"}},{"language":{"name":"ja-Hrkt","url":"/lang/1/"},"text":"ラジオきょくの　シャッターを　あける\nカードしきの　カギ。\n","version_group":{"name":"sun-moon","url":"/vg/17/"}},{"language":{"name":"ja","url":"/lang/11/"},"text":"ラジオ局の　シャッターを　開ける\nカード式の　カギ。\n","version_group":{"name":"x-y","url":"/vg/15/"}},{"language":{"name":"en","url":"/lang/9/"},"text":"A card key that opens a shutter in the\nRadio Tower.","version_group":{"name":"x-y","url":"/vg/15/"}},{"language":{"name":"it","url":"/lang/8/"},"text":"Chiave a scheda che apre le porte automatizzate\ndella Torre Radio.","version_group":{"name":"x-y","url":"/vg/15/"}},{"language":{"name":"es","url":"/lang/7/"},"text":"Poké Ball algo distinta, especialmente indicada\npara capturar los Pokémon que se han pescado\ncon una caña.","version_group":{"name":"x-y","url":"/vg/15/"}},{"language":{"name":"de","url":"/lang/6/"},"text":"Eine Schlüsselkarte, die eine\nTür im Radioturm öffnet.","version_group":{"name":"x-y","url":"/vg/15/"}},{"language":{"name":"fr","url":"/lang/5/"},"text":"Une clé en forme de carte permettant d’ouvrir\nles cloisons de la Tour Radio.","version_group":{"name":"x-y","url":"/vg/15/"}},{"language":{"name":"ko","url":"/lang/3/"},"text":"라디오방송국의 셔터를 여는\n카드식 열쇠.","version_group":{"name":"x-y","url":"/vg/15/"}},{"language":{"name":"ja-Hrkt","url":"/lang/1/"},"text":"ラジオきょくの　シャッターを　あける\nカードしきの　カギ。\n","version_group":{"name":"x-y","url":"/vg/15/"}},{"language":{"name":"en","url":"/lang/9/"},"text":"A card key that opens a shutter in the\nRadio Tower.","version_group":{"name":"black-2-white-2","url":"/vg/14/"}},{"language":{"name":"en","url":"/lang/9/"},"text":"A card key that opens a shutter in the\nRadio Tower.","version_group":{"name":"black-white","url":"/vg/11/"}},{"language":{"name":"fr","url":"/lang/5/"},"text":"Une clé en forme de carte permettant\nd’ouvrir les cloisons de la Tour Radio.","version_group":{"name":"black-white","url":"/vg/11/"}},{"language":{"name":"en","url":"/lang/9/"},"text":"A card key that opens a shutter in the\nRadio Tower.","version_group":{"name":"heartgold-soulsilver","url":"/vg/10/"}},{"language":{"name":"en","url":"/lang/9/"},"text":"A card-type key that unlocks doors\nin SILPH CO.’s HEAD OFFICE in\nSAFFRON CITY.","version_group":{"name":"firered-leafgreen","url":"/vg/7/"}},{"language":{"name":"en","url":"/lang/9/"},"text":"A card-type door\nkey used in SILPH\nCO’s office.","version_group":{"name":"emerald","url":"/vg/6/"}}],"fling_effect":null,"fling_power":null,"game_indices":[{"game_index":475,"generation":{"name":"sun-moon","url":"/gen/7/"}},{"game_index":475,"generation":{"name":"generation-vi","url":"/gen/6/"}},{"game_index":475,"generation":{"name":"generation-v","url":"/gen/5/"}},{"game_index":475,"generation":{"name":"generation-iv","url":"/gen/4/"}},{"game_index":355,"generation":{"name":"generation-iii","url":"/gen/3/"}}],"held_by_pokemon":[],"id":475,"machines":[],"name":"card-key","names":[{"language":{"name":"zh-Hans","url":"/lang/12/"},"name":"钥匙卡"},{"language":{"name":"ja","url":"/lang/11/"},"name":"カードキー"},{"language":{"name":"en","url":"/lang/9/"},"name":"Card Key"},{"language":{"name":"it","url":"/lang/8/"},"name":"Apriporta"},{"language":{"name":"es","url":"/lang/7/"},"name":"Llave Magnética"},{"language":{"name":"de","url":"/lang/6/"},"name":"Türöffner"},{"language":{"name":"fr","url":"/lang/5/"},"name":"Carte Magnétique"},{"language":{"name":"zh-Hant","url":"/lang/4/"},"name":"鑰匙卡"},{"language":{"name":"ko","url":"/lang/3/"},"name":"카드키"},{"language":{"name":"ja-Hrkt","url":"/lang/1/"},"name":"カードキー"}],"sprites":{"default":"/sprites/items/card-key.png"}}