{"effect_changes":[],"effect_entries":[{"effect":"Boosts Defense while grassy terrain is in effect.","language":{"name":"en","url":"/lang/9/"},"short_effect":"Boosts Defense while grassy terrain is in effect."}],"flavor_text_entries":[{"flavor_text":"在青草场地时，\n防御会提高。","language":{"name":"zh-Hans","url":"/lang/12/"},"version_group":{"name":"sun-moon","url":"/vg/17/"}},{"flavor_text":"グラスフィールドのとき\n防御が　上がる。","language":{"name":"ja","url":"/lang/11/"},"version_group":{"name":"sun-moon","url":"/vg/17/"}},{"flavor_text":"Boosts the Pokémon’s Defense stat in \nGrassy Terrain.","language":{"name":"en","url":"/lang/9/"},"version_group":{"name":"sun-moon","url":"/vg/17/"}},{"flavor_text":"In presenza di un Campo Erboso, la Difesa\naumenta.","language":{"name":"it","url":"/lang/8/"},"version_group":{"name":"sun-moon","url":"/vg/17/"}},{"flavor_text":"Aumenta la Defensa si hay un campo de hierba en el\nterreno de combate.","language":{"name":"es","url":"/lang/7/"},"version_group":{"name":"sun-moon","url":"/vg/17/"}},{"flavor_text":"Erhöht die Verteidigung, wenn Grasfeld aktiv ist.","language":{"name":"de","url":"/lang/6/"},"version_group":{"name":"sun-moon","url":"/vg/17/"}},{"flavor_text":"Augmente la Défense du Pokémon si Champ Herbu\nest actif.","language":{"name":"fr","url":"/lang/5/"},"version_group":{"name":"sun-moon","url":"/vg/17/"}},{"flavor_text":"在青草場地時，\n防禦會提高。","language":{"name":"zh-Hant","url":"/lang/4/"},"version_group":{"name":"sun-moon","url":"/vg/17/"}},{"flavor_text":"그래스필드일 때\n방어가 올라간다.","language":{"name":"ko","url":"/lang/3/"},"version_group":{"name":"sun-moon","url":"/vg/17/"}},{"flavor_text":"グラスフィールドのとき\nぼうぎょが　あがる。","language":{"name":"ja-Hrkt","url":"/lang/1/"},"version_group":{"name":"sun-moon","url":"/vg/17/"}},{"flavor_text":"グラスフィールドの時\n防御が　あがる。","language":{"name":"ja","url":"/lang/11/"},"version_group":{"name":"omega-ruby-alpha-sapphire","url":"/vg/16/"}},{"flavor_text":"Boosts the Defense stat\nin Grassy Terrain.","language":{"name":"en","url":"/lang/9/"},"version_group":{"name":"omega-ruby-alpha-sapphire","url":"/vg/16/"}},{"flavor_text":"Aumenta la Difesa durante\nl’effetto di Campo Erboso.","language":{"name":"it","url":"/lang/8/"},"version_group":{"name":"omega-ruby-alpha-sapphire","url":"/vg/16/"}},{"flavor_text":"Aumenta la Defensa mientras dura\nel efecto de Campo de Hierba.","language":{"name":"es","url":"/lang/7/"},"version_group":{"name":"omega-ruby-alpha-sapphire","url":"/vg/16/"}},{"flavor_text":"Erhöht die Verteidigung,\nwenn Grasfeld aktiv ist.","language":{"name":"de","url":"/lang/6/"},"version_group":{"name":"omega-ruby-alpha-sapphire","url":"/vg/16/"}},{"flavor_text":"Augmente la Défense si\nChamp Herbu est actif.","language":{"name":"fr","url":"/lang/5/"},"version_group":{"name":"omega-ruby-alpha-sapphire","url":"/vg/16/"}},{"flavor_text":"그래스필드일 때\n방어가 올라간다.","language":{"name":"ko","url":"/lang/3/"},"version_group":{"name":"omega-ruby-alpha-sapphire","url":"/vg/16/"}},{"flavor_text":"グラスフィールドのとき\nぼうぎょが　あがる。","language":{"name":"ja-Hrkt","url":"/lang/1/"},"version_group":{"name":"omega-ruby-alpha-sapphire","url":"/vg/16/"}},{"flavor_text":"グラスフィールドの時\n防御が　あがる。","language":{"name":"ja","url":"/lang/11/"},"version_group":{"name":"x-y","url":"/vg/15/"}},{"flavor_text":"Boosts the Defense stat\nin Grassy Terrain.","language":{"name":"en","url":"/lang/9/"},"version_group":{"name":"x-y","url":"/vg/15/"}},{"flavor_text":"Aumenta la Difesa durante\nl’effetto di Campo Erboso.","language":{"name":"it","url":"/lang/8/"},"version_group":{"name":"x-y","url":"/vg/15/"}},{"flavor_text":"Aumenta la Defensa mientras dura\nel efecto de Campo de Hierba.","language":{"name":"es","url":"/lang/7/"},"version_group":{"name":"x-y","url":"/vg/15/"}},{"flavor_text":"Erhöht die Verteidigung,\nwenn Grasfeld aktiv ist.","language":{"name":"de","url":"/lang/6/"},"version_group":{"name":"x-y","url":"/vg/15/"}},{"flavor_text":"Augmente la Défense si\nChamp Herbu est actif.","language":{"name":"fr","url":"/lang/5/"},"version_group":{"name":"x-y","url":"/vg/15/"}},{"flavor_text":"그래스필드일 때\n방어가 올라간다.","language":{"name":"ko","url":"/lang/3/"},"version_group":{"name":"x-y","url":"/vg/15/"}},{"flavor_text":"グラスフィールドのとき\nぼうぎょが　あがる。","language":{"name":"ja-Hrkt","url":"/lang/1/"},"version_group":{"name":"x-y","url":"/vg/15/"}}],"generation":{"name":"generation-vi","url":"/gen/6/"},"id":179,"is_main_series":true,"name":"grass-pelt","names":[{"language":{"name":"zh-Hans","url":"/lang/12/"},"name":"草之毛皮"},{"language":{"name":"ja","url":"/lang/11/"},"name":"くさのけがわ"},{"language":{"name":"en","url":"/lang/9/"},"name":"Grass Pelt"},{"language":{"name":"it","url":"/lang/8/"},"name":"Peloderba"},{"language":{"name":"es","url":"/lang/7/"},"name":"Manto Frondoso"},{"language":{"name":"de","url":"/lang/6/"},"name":"Pflanzenpelz"},{"language":{"name":"fr","url":"/lang/5/"},"name":"Toison Herbue"},{"language":{"name":"zh-Hant","url":"/lang/4/"},"name":"草之毛皮"},{"language":{"name":"ko","url":"/lang/3/"},"name":"풀모피"},{"language":{"name":"ja-Hrkt","url":"/lang/1/"},"name":"くさのけがわ"}],"pokemon":[{"is_hidden":true,"pokemon":{"name":"skiddo","url":"/p/672/"},"slot":3},{"is_hidden":true,"pokemon":{"name":"gogoat","url":"/p/673/"},"slot":3}]}