{"areas":[{"name":"kanto-altering-cave-a","url":"/loca/564/"},{"name":"kanto-altering-cave-b","url":"/loca/565/"},{"name":"kanto-altering-cave-c","url":"/loca/566/"},{"name":"kanto-altering-cave-d","url":"/loca/567/"},{"name":"kanto-altering-cave-e","url":"/loca/568/"},{"name":"kanto-altering-cave-f","url":"/loca/569/"},{"name":"kanto-altering-cave-g","url":"/loca/570/"},{"name":"kanto-altering-cave-h","url":"/loca/571/"},{"name":"kanto-altering-cave-i","url":"/loca/572/"}],"game_indices":[],"id":529,"name":"kanto-altering-cave","names":[{"language":{"name":"en","url":"/lang/9/"},"name":"Altering Cave"},{"language":{"name":"fr","url":"/lang/5/"},"name":"Grotte Métamo"}],"region":{"name":"kanto","url":"/r/1/"}}