{"attributes":[{"name":"holdable","url":"/ia/5/"},{"name":"usable-in-battle","url":"/ia/4/"},{"name":"usable-overworld","url":"/ia/3/"},{"name":"consumable","url":"/ia/2/"},{"name":"countable","url":"/ia/1/"}],"baby_trigger_for":null,"category":{"name":"healing","url":"/ic/27/"},"cost":200,"effect_entries":[{"effect":"Used on a party Pokémon\n:   Restores 50 HP.","language":{"name":"en","url":"/lang/9/"},"short_effect":"Restores 50 HP."}],"flavor_text_entries":[{"language":{"name":"zh-Hans","url":"/lang/12/"},"text":"富含矿物质的水。\n能让１只宝可梦\n回复３０ＨＰ。","version_group":{"name":"sun-moon","url":"/vg/17/"}},{"language":{"name":"ja","url":"/lang/11/"},"text":"ミネラル　たっぷりの　水。\nポケモン　１匹の　ＨＰを\n３０だけ　回復する。","version_group":{"name":"sun-moon","url":"/vg/17/"}},{"language":{"name":"en","url":"/lang/9/"},"text":"Water with a high mineral content. When consumed,\nit restores up to 30 HP to an injured Pokémon.","version_group":{"name":"sun-moon","url":"/vg/17/"}},{"language":{"name":"it","url":"/lang/8/"},"text":"Acqua ricca di sostanze minerali.\nRestituisce 30 PS a un Pokémon.","version_group":{"name":"sun-moon","url":"/vg/17/"}},{"language":{"name":"es","url":"/lang/7/"},"text":"Agua de alto contenido mineral que restaura 30 PS\nde un Pokémon.","version_group":{"name":"sun-moon","url":"/vg/17/"}},{"language":{"name":"de","url":"/lang/6/"},"text":"Ein stilles Wasser mit hohem Mineralienanteil,\ndas die KP eines Pokémon um 30 Punkte auffüllt.","version_group":{"name":"sun-moon","url":"/vg/17/"}},{"language":{"name":"fr","url":"/lang/5/"},"text":"Une eau riche en minéraux.\nRestaure 30 PV d’un Pokémon.","version_group":{"name":"sun-moon","url":"/vg/17/"}},{"language":{"name":"zh-Hant","url":"/lang/4/"},"text":"含有豐富礦物質的水。\n能讓１隻寶可夢\n回復３０ＨＰ。","version_group":{"name":"sun-moon","url":"/vg/17/"}},{"language":{"name":"ko","url":"/lang/3/"},"text":"미네랄이 가득한 물.\n포켓몬 1마리의 HP를\n30만큼 회복한다.","version_group":{"name":"sun-moon","url":"/vg/17/"}},{"language":{"name":"ja-Hrkt","url":"/lang/1/"},"text":"ミネラル　たっぷりの　みず。\nポケモン　１ひきの　ＨＰを\n３０だけ　かいふくする。","version_group":{"name":"sun-moon","url":"/vg/17/"}},{"language":{"name":"ja","url":"/lang/11/"},"text":"ミネラル　たっぷりの　水。\nポケモン　１匹の　ＨＰを\n５０だけ　回復する。","version_group":{"name":"x-y","url":"/vg/15/"}},{"language":{"name":"en","url":"/lang/9/"},"text":"Water with a high mineral content.\nWhen consumed, it restores\n50 HP to an injured Pokémon.","version_group":{"name":"x-y","url":"/vg/15/"}},{"language":{"name":"it","url":"/lang/8/"},"text":"Acqua ricca di sostanze minerali.\nRestituisce 50 PS a un Pokémon.","version_group":{"name":"x-y","url":"/vg/15/"}},{"language":{"name":"es","url":"/lang/7/"},"text":"Agua de alto contenido mineral que restaura\n50 PS de un Pokémon.","version_group":{"name":"x-y","url":"/vg/15/"}},{"language":{"name":"de","url":"/lang/6/"},"text":"Ein stilles Wasser mit hohem Mineralienanteil,\ndas die KP eines Pokémon um 50 Punkte auffüllt.","version_group":{"name":"x-y","url":"/vg/15/"}},{"language":{"name":"fr","url":"/lang/5/"},"text":"Une eau riche en minéraux.\nRestaure 50 PV d’un Pokémon.","version_group":{"name":"x-y","url":"/vg/15/"}},{"language":{"name":"ko","url":"/lang/3/"},"text":"미네랄이 가득한 물.\n포켓몬 1마리의 HP를\n50만큼 회복한다.","version_group":{"name":"x-y","url":"/vg/15/"}},{"language":{"name":"ja-Hrkt","url":"/lang/1/"},"text":"ミネラル　たっぷりの　みず。\nポケモン　１ひきの　ＨＰを\n５０だけ　かいふくする。","version_group":{"name":"x-y","url":"/vg/15/"}},{"language":{"name":"en","url":"/lang/9/"},"text":"Water with a high mineral content.\nIt restores the HP of one Pokémon by\n50 points.","version_group":{"name":"black-2-white-2","url":"/vg/14/"}},{"language":{"name":"en","url":"/lang/9/"},"text":"Water with a high mineral content.\nIt restores the HP of one Pokémon by\n50 points.","version_group":{"name":"black-white","url":"/vg/11/"}},{"language":{"name":"fr","url":"/lang/5/"},"text":"Une eau riche en minéraux.\nRestaure 50 PV à un Pokémon.","version_group":{"name":"black-white","url":"/vg/11/"}},{"language":{"name":"en","url":"/lang/9/"},"text":"Water with a high mineral content.\nIt restores the HP of one Pokémon by\n50 points.","version_group":{"name":"heartgold-soulsilver","url":"/vg/10/"}},{"language":{"name":"en","url":"/lang/9/"},"text":"Water with a high mineral content.\nIt restores the HP of one Pokémon by\n50 points.","version_group":{"name":"platinum","url":"/vg/9/"}},{"language":{"name":"en","url":"/lang/9/"},"text":"Water with a high mineral content.\nIt restores the HP of one Pokémon by\n50 points.","version_group":{"name":"diamond-pearl","url":"/vg/8/"}},{"language":{"name":"en","url":"/lang/9/"},"text":"Water with a high mineral content.\nIt restores the HP of one POKéMON\nby 50 points.","version_group":{"name":"firered-leafgreen","url":"/vg/7/"}},{"language":{"name":"en","url":"/lang/9/"},"text":"A mineral water\nthat restores HP\nby 50 points.","version_group":{"name":"emerald","url":"/vg/6/"}},{"language":{"name":"en","url":"/lang/9/"},"text":"A mineral water\nthat restores HP\nby 50 points.","version_group":{"name":"ruby-sapphire","url":"/vg/5/"}}],"fling_effect":null,"fling_power":30,"game_indices":[{"game_index":30,"generation":{"name":"sun-moon","url":"/gen/7/"}},{"game_index":30,"generation":{"name":"generation-vi","url":"/gen/6/"}},{"game_index":30,"generation":{"name":"generation-v","url":"/gen/5/"}},{"game_index":30,"generation":{"name":"generation-iv","url":"/gen/4/"}},{"game_index":26,"generation":{"name":"generation-iii","url":"/gen/3/"}}],"held_by_pokemon":[],"id":30,"machines":[],"name":"fresh-water","names":[{"language":{"name":"zh-Hans","url":"/lang/12/"},"name":"美味之水"},{"language":{"name":"ja","url":"/lang/11/"},"name":"おいしいみず"},{"language":{"name":"en","url":"/lang/9/"},"name":"Fresh Water"},{"language":{"name":"it","url":"/lang/8/"},"name":"Acqua Fresca"},{"language":{"name":"es","url":"/lang/7/"},"name":"Agua Fresca"},{"language":{"name":"de","url":"/lang/6/"},"name":"Tafelwasser"},{"language":{"name":"fr","url":"/lang/5/"},"name":"Eau Fraîche"},{"language":{"name":"zh-Hant","url":"/lang/4/"},"name":"美味之水"},{"language":{"name":"ko","url":"/lang/3/"},"name":"맛있는물"},{"language":{"name":"ja-Hrkt","url":"/lang/1/"},"name":"おいしいみず"}],"sprites":{"default":"/sprites/items/fresh-water.png"}}