{"form_name":"sunny","form_names":[{"language":{"name":"zh-Hans","url":"/lang/12/"},"name":"太阳的样子"},{"language":{"name":"ja","url":"/lang/11/"},"name":"たいようのすがた"},{"language":{"name":"en","url":"/lang/9/"},"name":"Sunny Form"},{"language":{"name":"it","url":"/lang/8/"},"name":"Forma Sole"},{"language":{"name":"es","url":"/lang/7/"},"name":"Forma Sol"},{"language":{"name":"de","url":"/lang/6/"},"name":"Sonnenform"},{"language":{"name":"fr","url":"/lang/5/"},"name":"Forme Solaire"},{"language":{"name":"zh-Hant","url":"/lang/4/"},"name":"太陽的樣子"},{"language":{"name":"ko","url":"/lang/3/"},"name":"태양의 모습"},{"language":{"name":"ja-Hrkt","url":"/lang/1/"},"name":"たいようのすがた"}],"form_order":2,"id":10028,"is_battle_only":true,"is_default":true,"is_mega":false,"name":"castform-sunny","names":[{"language":{"name":"en","url":"/lang/9/"},"name":"Sunny Castform"},{"language":{"name":"fr","url":"/lang/5/"},"name":"Morphéo Solaire"}],"order":467,"pokemon":{"name":"castform-sunny","url":"/p/10013/"},"sprites":{"back_default":"/sprites/pokemon/back/351-sunny.png","back_shiny":"/sprites/pokemon/back/shiny/351-sunny.png","front_default":"/sprites/pokemon/351-sunny.png","front_shiny":"/sprites/pokemon/shiny/351-sunny.png"},"version_group":{"name":"ruby-sapphire","url":"/vg/5/"}}