{"abilities":[{"ability":{"name":"rain-dish","url":"/a/44/"},"is_hidden":true,"slot":3},{"ability":{"name":"effect-spore","url":"/a/27/"},"is_hidden":false,"slot":2},{"ability":{"name":"illuminate","url":"/a/35/"},"is_hidden":false,"slot":1}],"base_experience":142,"forms":[{"name":"shiinotic","url":"/pf/756/"}],"game_indices":[],"height":10,"held_items":[{"item":{"name":"tiny-mushroom","url":"/i/86/"},"version_details":[{"rarity":50,"version":{"name":"moon","url":"/v/28/"}}]},{"item":{"name":"big-mushroom","url":"/i/87/"},"version_details":[{"rarity":5,"version":{"name":"moon","url":"/v/28/"}}]}],"id":756,"is_default":true,"location_area_encounters":"/p/756/encounters","moves":[{"move":{"name":"absorb","url":"/m/71/"},"version_group_details":[{"level_learned_at":1,"move_learn_method":{"name":"level-up","url":"/mlm/1/"},"version_group":{"name":"sun-moon","url":"/vg/17/"}}]},{"move":{"name":"mega-drain","url":"/m/72/"},"version_group_details":[{"level_learned_at":15,"move_learn_method":{"name":"level-up","url":"/mlm/1/"},"version_group":{"name":"sun-moon","url":"/vg/17/"}}]},{"move":{"name":"solar-beam","url":"/m/76/"},"version_group_details":[{"level_learned_at":0,"move_learn_method":{"name":"machine","url":"/mlm/4/"},"version_group":{"name":"sun-moon","url":"/vg/17/"}}]},{"move":{"name":"sleep-powder","url":"/m/79/"},"version_group_details":[{"level_learned_at":18,"move_learn_method":{"name":"level-up","url":"/mlm/1/"},"version_group":{"name":"sun-moon","url":"/vg/17/"}}]},{"move":{"name":"thunder-wave","url":"/m/86/"},"version_group_details":[{"level_learned_at":0,"move_learn_method":{"name":"machine","url":"/mlm/4/"},"version_group":{"name":"sun-moon","url":"/vg/17/"}}]},{"move":{"name":"toxic","url":"/m/92/"},"version_group_details":[{"level_learned_at":0,"move_learn_method":{"name":"machine","url":"/mlm/4/"},"version_group":{"name":"sun-moon","url":"/vg/17/"}}]},{"move":{"name":"double-team","url":"/m/104/"},"version_group_details":[{"level_learned_at":0,"move_learn_method":{"name":"machine","url":"/mlm/4/"},"version_group":{"name":"sun-moon","url":"/vg/17/"}}]},{"move":{"name":"confuse-ray","url":"/m/109/"},"version_group_details":[{"level_learned_at":26,"move_learn_method":{"name":"level-up","url":"/mlm/1/"},"version_group":{"name":"sun-moon","url":"/vg/17/"}}]},{"move":{"name":"light-screen","url":"/m/113/"},"version_group_details":[{"level_learned_at":0,"move_learn_method":{"name":"machine","url":"/mlm/4/"},"version_group":{"name":"sun-moon","url":"/vg/17/"}}]},{"move":{"name":"dream-eater","url":"/m/138/"},"version_group_details":[{"level_learned_at":0,"move_learn_method":{"name":"machine","url":"/mlm/4/"},"version_group":{"name":"sun-moon","url":"/vg/17/"}},{"level_learned_at":49,"move_learn_method":{"name":"level-up","url":"/mlm/1/"},"version_group":{"name":"sun-moon","url":"/vg/17/"}}]},{"move":{"name":"spore","url":"/m/147/"},"version_group_details":[{"level_learned_at":40,"move_learn_method":{"name":"level-up","url":"/mlm/1/"},"version_group":{"name":"sun-moon","url":"/vg/17/"}}]},{"move":{"name":"flash","url":"/m/148/"},"version_group_details":[{"level_learned_at":8,"move_learn_method":{"name":"level-up","url":"/mlm/1/"},"version_group":{"name":"sun-moon","url":"/vg/17/"}},{"level_learned_at":1,"move_learn_method":{"name":"level-up","url":"/mlm/1/"},"version_group":{"name":"sun-moon","url":"/vg/17/"}}]},{"move":{"name":"rest","url":"/m/156/"},"version_group_details":[{"level_learned_at":0,"move_learn_method":{"name":"machine","url":"/mlm/4/"},"version_group":{"name":"sun-moon","url":"/vg/17/"}}]},{"move":{"name":"substitute","url":"/m/164/"},"version_group_details":[{"level_learned_at":0,"move_learn_method":{"name":"machine","url":"/mlm/4/"},"version_group":{"name":"sun-moon","url":"/vg/17/"}}]},{"move":{"name":"protect","url":"/m/182/"},"version_group_details":[{"level_learned_at":0,"move_learn_method":{"name":"machine","url":"/mlm/4/"},"version_group":{"name":"sun-moon","url":"/vg/17/"}}]},{"move":{"name":"sludge-bomb","url":"/m/188/"},"version_group_details":[{"level_learned_at":0,"move_learn_method":{"name":"machine","url":"/mlm/4/"},"version_group":{"name":"sun-moon","url":"/vg/17/"}}]},{"move":{"name":"giga-drain","url":"/m/202/"},"version_group_details":[{"level_learned_at":31,"move_learn_method":{"name":"level-up","url":"/mlm/1/"},"version_group":{"name":"sun-moon","url":"/vg/17/"}}]},{"move":{"name":"swagger","url":"/m/207/"},"version_group_details":[{"level_learned_at":0,"move_learn_method":{"name":"machine","url":"/mlm/4/"},"version_group":{"name":"sun-moon","url":"/vg/17/"}}]},{"move":{"name":"attract","url":"/m/213/"},"version_group_details":[{"level_learned_at":0,"move_learn_method":{"name":"machine","url":"/mlm/4/"},"version_group":{"name":"sun-moon","url":"/vg/17/"}}]},{"move":{"name":"sleep-talk","url":"/m/214/"},"version_group_details":[{"level_learned_at":0,"move_learn_method":{"name":"machine","url":"/mlm/4/"},"version_group":{"name":"sun-moon","url":"/vg/17/"}}]},{"move":{"name":"return","url":"/m/216/"},"version_group_details":[{"level_learned_at":0,"move_learn_method":{"name":"machine","url":"/mlm/4/"},"version_group":{"name":"sun-moon","url":"/vg/17/"}}]},{"move":{"name":"frustration","url":"/m/218/"},"version_group_details":[{"level_learned_at":0,"move_learn_method":{"name":"machine","url":"/mlm/4/"},"version_group":{"name":"sun-moon","url":"/vg/17/"}}]},{"move":{"name":"safeguard","url":"/m/219/"},"version_group_details":[{"level_learned_at":0,"move_learn_method":{"name":"machine","url":"/mlm/4/"},"version_group":{"name":"sun-moon","url":"/vg/17/"}}]},{"move":{"name":"moonlight","url":"/m/236/"},"version_group_details":[{"level_learned_at":11,"move_learn_method":{"name":"level-up","url":"/mlm/1/"},"version_group":{"name":"sun-moon","url":"/vg/17/"}}]},{"move":{"name":"hidden-power","url":"/m/237/"},"version_group_details":[{"level_learned_at":0,"move_learn_method":{"name":"machine","url":"/mlm/4/"},"version_group":{"name":"sun-moon","url":"/vg/17/"}}]},{"move":{"name":"nature-power","url":"/m/267/"},"version_group_details":[{"level_learned_at":0,"move_learn_method":{"name":"machine","url":"/mlm/4/"},"version_group":{"name":"sun-moon","url":"/vg/17/"}}]},{"move":{"name":"ingrain","url":"/m/275/"},"version_group_details":[{"level_learned_at":22,"move_learn_method":{"name":"level-up","url":"/mlm/1/"},"version_group":{"name":"sun-moon","url":"/vg/17/"}},{"level_learned_at":1,"move_learn_method":{"name":"level-up","url":"/mlm/1/"},"version_group":{"name":"sun-moon","url":"/vg/17/"}}]},{"move":{"name":"astonish","url":"/m/310/"},"version_group_details":[{"level_learned_at":4,"move_learn_method":{"name":"level-up","url":"/mlm/1/"},"version_group":{"name":"sun-moon","url":"/vg/17/"}},{"level_learned_at":1,"move_learn_method":{"name":"level-up","url":"/mlm/1/"},"version_group":{"name":"sun-moon","url":"/vg/17/"}}]},{"move":{"name":"energy-ball","url":"/m/412/"},"version_group_details":[{"level_learned_at":0,"move_learn_method":{"name":"machine","url":"/mlm/4/"},"version_group":{"name":"sun-moon","url":"/vg/17/"}}]},{"move":{"name":"giga-impact","url":"/m/416/"},"version_group_details":[{"level_learned_at":0,"move_learn_method":{"name":"machine","url":"/mlm/4/"},"version_group":{"name":"sun-moon","url":"/vg/17/"}}]},{"move":{"name":"grass-knot","url":"/m/447/"},"version_group_details":[{"level_learned_at":0,"move_learn_method":{"name":"machine","url":"/mlm/4/"},"version_group":{"name":"sun-moon","url":"/vg/17/"}}]},{"move":{"name":"charge-beam","url":"/m/451/"},"version_group_details":[{"level_learned_at":0,"move_learn_method":{"name":"machine","url":"/mlm/4/"},"version_group":{"name":"sun-moon","url":"/vg/17/"}}]},{"move":{"name":"round","url":"/m/496/"},"version_group_details":[{"level_learned_at":0,"move_learn_method":{"name":"machine","url":"/mlm/4/"},"version_group":{"name":"sun-moon","url":"/vg/17/"}}]},{"move":{"name":"moonblast","url":"/m/585/"},"version_group_details":[{"level_learned_at":44,"move_learn_method":{"name":"level-up","url":"/mlm/1/"},"version_group":{"name":"sun-moon","url":"/vg/17/"}}]},{"move":{"name":"confide","url":"/m/590/"},"version_group_details":[{"level_learned_at":0,"move_learn_method":{"name":"machine","url":"/mlm/4/"},"version_group":{"name":"sun-moon","url":"/vg/17/"}}]},{"move":{"name":"dazzling-gleam","url":"/m/605/"},"version_group_details":[{"level_learned_at":0,"move_learn_method":{"name":"machine","url":"/mlm/4/"},"version_group":{"name":"sun-moon","url":"/vg/17/"}}]},{"move":{"name":"strength-sap","url":"/m/668/"},"version_group_details":[{"level_learned_at":35,"move_learn_method":{"name":"level-up","url":"/mlm/1/"},"version_group":{"name":"sun-moon","url":"/vg/17/"}}]},{"move":{"name":"spotlight","url":"/m/671/"},"version_group_details":[{"level_learned_at":53,"move_learn_method":{"name":"level-up","url":"/mlm/1/"},"version_group":{"name":"sun-moon","url":"/vg/17/"}}]}],"name":"shiinotic","order":878,"species":{"name":"shiinotic","url":"/psp/756/"},"sprites":{"back_default":null,"back_female":null,"back_shiny":null,"back_shiny_female":null,"front_default":"/sprites/pokemon/756.png","front_female":null,"front_shiny":"/sprites/pokemon/shiny/756.png","front_shiny_female":null},"stats":[{"base_stat":30,"effort":0,"stat":{"name":"speed","url":"/s/6/"}},{"base_stat":100,"effort":2,"stat":{"name":"special-defense","url":"/s/5/"}},{"base_stat":90,"effort":0,"stat":{"name":"special-attack","url":"/s/4/"}},{"base_stat":80,"effort":0,"stat":{"name":"defense","url":"/s/3/"}},{"base_stat":45,"effort":0,"stat":{"name":"attack","url":"/s/2/"}},{"base_stat":60,"effort":0,"stat":{"name":"hp","url":"/s/1/"}}],"types":[{"slot":2,"type":{"name":"fairy","url":"/t/18/"}},{"slot":1,"type":{"name":"grass","url":"/t/12/"}}],"weight":115}