{"attributes":[],"baby_trigger_for":null,"category":{"name":"all-machines","url":"/ic/37/"},"cost":10000,"effect_entries":[{"effect":"Teaches Focus Punch to a compatible Pokémon.","language":{"name":"en","url":"/lang/9/"},"short_effect":"Teaches Hone Claws to a compatible Pokémon. (Gen IV & III: Focus Punch Gen II: DynamicPunch Gen I: Mega Punch)"}],"flavor_text_entries":[{"language":{"name":"zh-Hans","url":"/lang/12/"},"text":"激励自己，\n从而提高攻击和特攻。","version_group":{"name":"sun-moon","url":"/vg/17/"}},{"language":{"name":"ja","url":"/lang/11/"},"text":"自分を　奮いたてて\n攻撃と　特攻を　あげる。\n","version_group":{"name":"sun-moon","url":"/vg/17/"}},{"language":{"name":"en","url":"/lang/9/"},"text":"The user is roused, and its Attack and Sp. Atk\nstats increase.","version_group":{"name":"sun-moon","url":"/vg/17/"}},{"language":{"name":"it","url":"/lang/8/"},"text":"Chi la usa si tira su di morale, aumentando\nil proprio Attacco e l’Attacco Speciale.","version_group":{"name":"sun-moon","url":"/vg/17/"}},{"language":{"name":"es","url":"/lang/7/"},"text":"Lima y afila las garras. Aumenta el Ataque y la\nPrecisión.","version_group":{"name":"sun-moon","url":"/vg/17/"}},{"language":{"name":"de","url":"/lang/6/"},"text":"Anwender erhält einen Kraftschub, der seinen\nAngriff und Spezial-Angriff erhöht.","version_group":{"name":"sun-moon","url":"/vg/17/"}},{"language":{"name":"fr","url":"/lang/5/"},"text":"Le lanceur se rengorge.\nAugmente l’Attaque et l’Attaque Spéciale.","version_group":{"name":"sun-moon","url":"/vg/17/"}},{"language":{"name":"zh-Hant","url":"/lang/4/"},"text":"激勵自己，\n進而提高攻擊和特攻。","version_group":{"name":"sun-moon","url":"/vg/17/"}},{"language":{"name":"ko","url":"/lang/3/"},"text":"스스로 분발해서\n공격과 특수공격을 올린다.","version_group":{"name":"sun-moon","url":"/vg/17/"}},{"language":{"name":"ja-Hrkt","url":"/lang/1/"},"text":"じぶんを　ふるいたてて\nこうげきと　とくこうを　あげる。\n","version_group":{"name":"sun-moon","url":"/vg/17/"}},{"language":{"name":"ja","url":"/lang/11/"},"text":"つめを　磨いて　鋭く　する。\n自分の　攻撃と\n命中率を　あげる。","version_group":{"name":"x-y","url":"/vg/15/"}},{"language":{"name":"en","url":"/lang/9/"},"text":"The user sharpens its claws to\nboost its Attack stat and accuracy.","version_group":{"name":"x-y","url":"/vg/15/"}},{"language":{"name":"it","url":"/lang/8/"},"text":"Chi la usa affila i propri artigli, aumentando\nAttacco e precisione.","version_group":{"name":"x-y","url":"/vg/15/"}},{"language":{"name":"es","url":"/lang/7/"},"text":"Quien lo usa invoca una fuerte lluvia que dura\ncinco turnos y fortalece los movimientos de tipo\nAgua.","version_group":{"name":"x-y","url":"/vg/15/"}},{"language":{"name":"de","url":"/lang/6/"},"text":"Der Anwender wetzt seine Klauen, um sie zu\nschärfen. Angriff und Genauigkeit werden erhöht.","version_group":{"name":"x-y","url":"/vg/15/"}},{"language":{"name":"fr","url":"/lang/5/"},"text":"Le lanceur s’aiguise les griffes.\nAugmente l’Attaque et la Précision.","version_group":{"name":"x-y","url":"/vg/15/"}},{"language":{"name":"ko","url":"/lang/3/"},"text":"손톱을 갈아 날카롭게 만든다.\n자신의 공격과\n명중률을 올린다.","version_group":{"name":"x-y","url":"/vg/15/"}},{"language":{"name":"ja-Hrkt","url":"/lang/1/"},"text":"つめを　みがいて　するどく　する。\nじぶんの　こうげきと\nめいちゅうりつを　あげる。","version_group":{"name":"x-y","url":"/vg/15/"}},{"language":{"name":"en","url":"/lang/9/"},"text":"The user sharpens its claws to\nboost its Attack stat and accuracy.","version_group":{"name":"black-2-white-2","url":"/vg/14/"}},{"language":{"name":"en","url":"/lang/9/"},"text":"The user sharpens its claws to\nboost its Attack stat and accuracy.","version_group":{"name":"black-white","url":"/vg/11/"}},{"language":{"name":"fr","url":"/lang/5/"},"text":"Le lanceur s’aiguise les griffes.\nAugmente l’Attaque et la Précision.","version_group":{"name":"black-white","url":"/vg/11/"}},{"language":{"name":"en","url":"/lang/9/"},"text":"The user focuses its mind before\nlaunching this attack. It will fail if\nthe user is hit before it is used.","version_group":{"name":"heartgold-soulsilver","url":"/vg/10/"}},{"language":{"name":"en","url":"/lang/9/"},"text":"The user focuses its mind before\nlaunching this attack. It will fail if\nthe user is hit before it is used.","version_group":{"name":"platinum","url":"/vg/9/"}},{"language":{"name":"en","url":"/lang/9/"},"text":"The user focuses its mind before\nlaunching this attack. It will fail if\nthe user is hit before it is used.","version_group":{"name":"diamond-pearl","url":"/vg/8/"}},{"language":{"name":"en","url":"/lang/9/"},"text":"An attack that is\nexecuted last.\nThe user flinches\nif hit beforehand.","version_group":{"name":"firered-leafgreen","url":"/vg/7/"}},{"language":{"name":"en","url":"/lang/9/"},"text":"Powerful, but makes\nthe user flinch if\nhit by the foe.","version_group":{"name":"emerald","url":"/vg/6/"}},{"language":{"name":"en","url":"/lang/9/"},"text":"Powerful, but makes\nthe user flinch if\nhit by the foe.","version_group":{"name":"ruby-sapphire","url":"/vg/5/"}}],"fling_effect":null,"fling_power":null,"game_indices":[{"game_index":328,"generation":{"name":"sun-moon","url":"/gen/7/"}},{"game_index":328,"generation":{"name":"generation-vi","url":"/gen/6/"}},{"game_index":328,"generation":{"name":"generation-v","url":"/gen/5/"}},{"game_index":328,"generation":{"name":"generation-iv","url":"/gen/4/"}},{"game_index":289,"generation":{"name":"generation-iii","url":"/gen/3/"}}],"held_by_pokemon":[],"id":305,"machines":[{"machine":{"url":"/mac/17/"},"version_group":{"name":"sun-moon","url":"/vg/17/"}},{"machine":{"url":"/mac/16/"},"version_group":{"name":"omega-ruby-alpha-sapphire","url":"/vg/16/"}},{"machine":{"url":"/mac/15/"},"version_group":{"name":"x-y","url":"/vg/15/"}},{"machine":{"url":"/mac/14/"},"version_group":{"name":"black-2-white-2","url":"/vg/14/"}},{"machine":{"url":"/mac/13/"},"version_group":{"name":"xd","url":"/vg/13/"}},{"machine":{"url":"/mac/12/"},"version_group":{"name":"colosseum","url":"/vg/12/"}},{"machine":{"url":"/mac/11/"},"version_group":{"name":"black-white","url":"/vg/11/"}},{"machine":{"url":"/mac/10/"},"version_group":{"name":"heartgold-soulsilver","url":"/vg/10/"}},{"machine":{"url":"/mac/9/"},"version_group":{"name":"platinum","url":"/vg/9/"}},{"machine":{"url":"/mac/8/"},"version_group":{"name":"diamond-pearl","url":"/vg/8/"}},{"machine":{"url":"/mac/7/"},"version_group":{"name":"firered-leafgreen","url":"/vg/7/"}},{"machine":{"url":"/mac/6/"},"version_group":{"name":"emerald","url":"/vg/6/"}},{"machine":{"url":"/mac/5/"},"version_group":{"name":"ruby-sapphire","url":"/vg/5/"}},{"machine":{"url":"/mac/4/"},"version_group":{"name":"crystal","url":"/vg/4/"}},{"machine":{"url":"/mac/3/"},"version_group":{"name":"gold-silver","url":"/vg/3/"}},{"machine":{"url":"/mac/2/"},"version_group":{"name":"yellow","url":"/vg/2/"}},{"machine":{"url":"/mac/1/"},"version_group":{"name":"red-blue","url":"/vg/1/"}}],"name":"tm01","names":[{"language":{"name":"zh-Hans","url":"/lang/12/"},"name":"招式学习器０１"},{"language":{"name":"ja","url":"/lang/11/"},"name":"わざマシン０１"},{"language":{"name":"en","url":"/lang/9/"},"name":"TM01"},{"language":{"name":"it","url":"/lang/8/"},"name":"MT01"},{"language":{"name":"es","url":"/lang/7/"},"name":"MT01"},{"language":{"name":"de","url":"/lang/6/"},"name":"TM01"},{"language":{"name":"fr","url":"/lang/5/"},"name":"CT01"},{"language":{"name":"zh-Hant","url":"/lang/4/"},"name":"招式學習器０１"},{"language":{"name":"ko","url":"/lang/3/"},"name":"기술머신01"},{"language":{"name":"ja-Hrkt","url":"/lang/1/"},"name":"わざマシン０１"}],"sprites":{"default":"/sprites/items/tm-normal.png"}}