{"accuracy":75,"contest_combos":{"normal":{"use_after":[{"name":"soft-boiled","url":"/m/135/"}],"use_before":null},"super":{"use_after":null,"use_before":null}},"contest_effect":{"url":"/ce/1/"},"contest_type":{"name":"tough","url":"/ct/5/"},"damage_class":{"name":"physical","url":"/mdc/2/"},"effect_chance":null,"effect_changes":[],"effect_entries":[{"effect":"Inflicts regular damage.","language":{"name":"en","url":"/lang/9/"},"short_effect":"Inflicts regular damage with no additional effect."}],"flavor_text_entries":[{"flavor_text":"向对手用力投掷\n大大的蛋进行攻击。","language":{"name":"zh-Hans","url":"/lang/12/"},"version_group":{"name":"sun-moon","url":"/vg/17/"}},{"flavor_text":"大きな　タマゴを　力いっぱい\n相手に　投げつけて　攻撃する。","language":{"name":"ja","url":"/lang/11/"},"version_group":{"name":"sun-moon","url":"/vg/17/"}},{"flavor_text":"A large egg is hurled at the target with maximum\nforce to inflict damage.","language":{"name":"en","url":"/lang/9/"},"version_group":{"name":"sun-moon","url":"/vg/17/"}},{"flavor_text":"Colpisce il bersaglio con un grande uovo\nscaraventato con enorme forza.","language":{"name":"it","url":"/lang/8/"},"version_group":{"name":"sun-moon","url":"/vg/17/"}},{"flavor_text":"Arroja un huevo enorme al objetivo con gran fuerza. ","language":{"name":"es","url":"/lang/7/"},"version_group":{"name":"sun-moon","url":"/vg/17/"}},{"flavor_text":"Ein großes Ei wird auf das Ziel abgefeuert, um ihm zu\nschaden.","language":{"name":"de","url":"/lang/6/"},"version_group":{"name":"sun-moon","url":"/vg/17/"}},{"flavor_text":"De toutes ses forces, le lanceur jette un gros œuf\nsur l’ennemi pour lui infliger des dégâts.","language":{"name":"fr","url":"/lang/5/"},"version_group":{"name":"sun-moon","url":"/vg/17/"}},{"flavor_text":"向對手用力投擲\n大大的蛋進行攻擊。","language":{"name":"zh-Hant","url":"/lang/4/"},"version_group":{"name":"sun-moon","url":"/vg/17/"}},{"flavor_text":"큰 알을 온 힘을 다해\n상대에게 내던져서 공격한다.","language":{"name":"ko","url":"/lang/3/"},"version_group":{"name":"sun-moon","url":"/vg/17/"}},{"flavor_text":"おおきな　タマゴを　ちから　いっぱい\nあいてに　なげつけて　こうげきする。","language":{"name":"ja-Hrkt","url":"/lang/1/"},"version_group":{"name":"sun-moon","url":"/vg/17/"}},{"flavor_text":"大きな　タマゴを　力いっぱい\n相手に　投げつけて　攻撃する。\n","language":{"name":"ja","url":"/lang/11/"},"version_group":{"name":"omega-ruby-alpha-sapphire","url":"/vg/16/"}},{"flavor_text":"A large egg is hurled at the target\nwith maximum force to inflict damage.","language":{"name":"en","url":"/lang/9/"},"version_group":{"name":"omega-ruby-alpha-sapphire","url":"/vg/16/"}},{"flavor_text":"Colpisce il bersaglio con un grande uovo\nscaraventato con enorme forza.","language":{"name":"it","url":"/lang/8/"},"version_group":{"name":"omega-ruby-alpha-sapphire","url":"/vg/16/"}},{"flavor_text":"Arroja un huevo al objetivo con gran fuerza. ","language":{"name":"es","url":"/lang/7/"},"version_group":{"name":"omega-ruby-alpha-sapphire","url":"/vg/16/"}},{"flavor_text":"Ein großes Ei wird auf das Ziel abgefeuert,\num ihm zu schaden.","language":{"name":"de","url":"/lang/6/"},"version_group":{"name":"omega-ruby-alpha-sapphire","url":"/vg/16/"}},{"flavor_text":"De toutes ses forces, le lanceur jette un gros œuf\nsur l’ennemi pour lui infliger des dégâts.","language":{"name":"fr","url":"/lang/5/"},"version_group":{"name":"omega-ruby-alpha-sapphire","url":"/vg/16/"}},{"flavor_text":"큰 알을 온 힘을 다해\n상대에게 내던져서 공격한다.","language":{"name":"ko","url":"/lang/3/"},"version_group":{"name":"omega-ruby-alpha-sapphire","url":"/vg/16/"}},{"flavor_text":"おおきな　タマゴを　ちから　いっぱい\nあいてに　なげつけて　こうげきする。\n","language":{"name":"ja-Hrkt","url":"/lang/1/"},"version_group":{"name":"omega-ruby-alpha-sapphire","url":"/vg/16/"}},{"flavor_text":"大きな　タマゴを　力いっぱい\n相手に　投げつけて　攻撃する。\n","language":{"name":"ja","url":"/lang/11/"},"version_group":{"name":"x-y","url":"/vg/15/"}},{"flavor_text":"A large egg is hurled at the target\nwith maximum force to inflict damage.","language":{"name":"en","url":"/lang/9/"},"version_group":{"name":"x-y","url":"/vg/15/"}},{"flavor_text":"Colpisce il bersaglio con un grande uovo\nscaraventato con enorme forza.","language":{"name":"it","url":"/lang/8/"},"version_group":{"name":"x-y","url":"/vg/15/"}},{"flavor_text":"Arroja un huevo al objetivo con gran fuerza.","language":{"name":"es","url":"/lang/7/"},"version_group":{"name":"x-y","url":"/vg/15/"}},{"flavor_text":"Ein großes Ei wird auf das Ziel abgefeuert,\num ihm zu schaden.","language":{"name":"de","url":"/lang/6/"},"version_group":{"name":"x-y","url":"/vg/15/"}},{"flavor_text":"De toutes ses forces, le lanceur jette un gros œuf\nsur l’ennemi pour lui infliger des dégâts.","language":{"name":"fr","url":"/lang/5/"},"version_group":{"name":"x-y","url":"/vg/15/"}},{"flavor_text":"큰 알을 온 힘을 다해\n상대에게 내던져서 공격한다.","language":{"name":"ko","url":"/lang/3/"},"version_group":{"name":"x-y","url":"/vg/15/"}},{"flavor_text":"おおきな　タマゴを　ちから　いっぱい\nあいてに　なげつけて　こうげきする。\n","language":{"name":"ja-Hrkt","url":"/lang/1/"},"version_group":{"name":"x-y","url":"/vg/15/"}},{"flavor_text":"A large egg is hurled at the target\nwith maximum force to inflict damage.","language":{"name":"en","url":"/lang/9/"},"version_group":{"name":"black-2-white-2","url":"/vg/14/"}},{"flavor_text":"A large egg is hurled at the target\nwith maximum force to inflict damage.","language":{"name":"en","url":"/lang/9/"},"version_group":{"name":"black-white","url":"/vg/11/"}},{"flavor_text":"De toutes ses forces, le lanceur\njette un gros œuf sur l’ennemi\npour lui infliger des dégâts.","language":{"name":"fr","url":"/lang/5/"},"version_group":{"name":"black-white","url":"/vg/11/"}},{"flavor_text":"A large egg is hurled\nwith maximum force at\nthe foe to inflict\ndamage.\n","language":{"name":"en","url":"/lang/9/"},"version_group":{"name":"heartgold-soulsilver","url":"/vg/10/"}},{"flavor_text":"A large egg is hurled\nwith maximum force at\nthe foe to inflict\ndamage.\n","language":{"name":"en","url":"/lang/9/"},"version_group":{"name":"platinum","url":"/vg/9/"}},{"flavor_text":"A large egg is hurled\nwith maximum force at\nthe foe to inflict\ndamage.\n","language":{"name":"en","url":"/lang/9/"},"version_group":{"name":"diamond-pearl","url":"/vg/8/"}},{"flavor_text":"A large egg is\nhurled with great\nforce at the foe to\ninflict damage.","language":{"name":"en","url":"/lang/9/"},"version_group":{"name":"firered-leafgreen","url":"/vg/7/"}},{"flavor_text":"An egg is forcibly hurled at\nthe foe.","language":{"name":"en","url":"/lang/9/"},"version_group":{"name":"emerald","url":"/vg/6/"}},{"flavor_text":"An egg is forcibly hurled at\nthe foe.","language":{"name":"en","url":"/lang/9/"},"version_group":{"name":"ruby-sapphire","url":"/vg/5/"}},{"flavor_text":"Eggs are hurled at\nthe foe.","language":{"name":"en","url":"/lang/9/"},"version_group":{"name":"crystal","url":"/vg/4/"}},{"flavor_text":"Eggs are hurled at\nthe foe.","language":{"name":"en","url":"/lang/9/"},"version_group":{"name":"gold-silver","url":"/vg/3/"}}],"generation":{"name":"generation-i","url":"/gen/1/"},"id":121,"machines":[{"machine":{"url":"/mac/613/"},"version_group":{"name":"red-blue","url":"/vg/1/"}},{"machine":{"url":"/mac/614/"},"version_group":{"name":"yellow","url":"/vg/2/"}}],"meta":{"ailment":{"name":"none","url":"/ma/0/"},"ailment_chance":0,"category":{"name":"damage","url":"/mc/0/"},"crit_rate":0,"drain":0,"flinch_chance":0,"healing":0,"max_hits":null,"max_turns":null,"min_hits":null,"min_turns":null,"stat_chance":0},"name":"egg-bomb","names":[{"language":{"name":"zh-Hans","url":"/lang/12/"},"name":"炸蛋"},{"language":{"name":"ja","url":"/lang/11/"},"name":"タマゴばくだん"},{"language":{"name":"en","url":"/lang/9/"},"name":"Egg Bomb"},{"language":{"name":"it","url":"/lang/8/"},"name":"Uovobomba"},{"language":{"name":"es","url":"/lang/7/"},"name":"Bomba Huevo"},{"language":{"name":"de","url":"/lang/6/"},"name":"Eierbombe"},{"language":{"name":"fr","url":"/lang/5/"},"name":"Bomb’Œuf"},{"language":{"name":"zh-Hant","url":"/lang/4/"},"name":"炸蛋"},{"language":{"name":"ko","url":"/lang/3/"},"name":"알폭탄"},{"language":{"name":"ja-Hrkt","url":"/lang/1/"},"name":"タマゴばくだん"}],"past_values":[],"power":100,"pp":10,"priority":0,"stat_changes":[],"super_contest_effect":{"url":"/sce/5/"},"target":{"name":"selected-pokemon","url":"/mt/10/"},"type":{"name":"normal","url":"/t/1/"}}