{"encounter_method_rates":[],"game_index":0,"id":712,"location":{"name":"laverre-city","url":"/loc/633/"},"name":"laverre-city-area","names":[],"pokemon_encounters":[{"pokemon":{"name":"poliwag","url":"/p/60/"},"version_details":[{"encounter_details":[{"chance":5,"condition_values":[],"max_level":15,"method":{"name":"old-rod","url":"/em/2/"},"min_level":15},{"chance":35,"condition_values":[],"max_level":15,"method":{"name":"old-rod","url":"/em/2/"},"min_level":15},{"chance":60,"condition_values":[],"max_level":15,"method":{"name":"old-rod","url":"/em/2/"},"min_level":15}],"max_chance":100,"version":{"name":"x","url":"/v/23/"}},{"encounter_details":[{"chance":5,"condition_values":[],"max_level":15,"method":{"name":"old-rod","url":"/em/2/"},"min_level":15},{"chance":35,"condition_values":[],"max_level":15,"method":{"name":"old-rod","url":"/em/2/"},"min_level":15},{"chance":60,"condition_values":[],"max_level":15,"method":{"name":"old-rod","url":"/em/2/"},"min_level":15}],"max_chance":100,"version":{"name":"y","url":"/v/24/"}}]},{"pokemon":{"name":"poliwhirl","url":"/p/61/"},"version_details":[{"encounter_details":[{"chance":35,"condition_values":[],"max_level":25,"method":{"name":"good-rod","url":"/em/3/"},"min_level":25},{"chance":60,"condition_values":[],"max_level":35,"method":{"name":"super-rod","url":"/em/4/"},"min_level":35},{"chance":5,"condition_values":[],"max_level":35,"method":{"name":"super-rod","url":"/em/4/"},"min_level":35}],"max_chance":100,"version":{"name":"x","url":"/v/23/"}},{"encounter_details":[{"chance":35,"condition_values":[],"max_level":25,"method":{"name":"good-rod","url":"/em/3/"},"min_level":25},{"chance":60,"condition_values":[],"max_level":35,"method":{"name":"super-rod","url":"/em/4/"},"min_level":35},{"chance":5,"condition_values":[],"max_level":35,"method":{"name":"super-rod","url":"/em/4/"},"min_level":35}],"max_chance":100,"version":{"name":"y","url":"/v/24/"}}]},{"pokemon":{"name":"basculin-red-striped","url":"/p/550/"},"version_details":[{"encounter_details":[{"chance":35,"condition_values":[],"max_level":35,"method":{"name":"super-rod","url":"/em/4/"},"min_level":35}],"max_chance":35,"version":{"name":"x","url":"/v/23/"}},{"encounter_details":[{"chance":60,"condition_values":[],"max_level":25,"method":{"name":"good-rod","url":"/em/3/"},"min_level":25},{"chance":5,"condition_values":[],"max_level":25,"method":{"name":"good-rod","url":"/em/3/"},"min_level":25}],"max_chance":65,"version":{"name":"y","url":"/v/24/"}}]},{"pokemon":{"name":"basculin-blue-striped","url":"/p/10016/"},"version_details":[{"encounter_details":[{"chance":60,"condition_values":[],"max_level":25,"method":{"name":"good-rod","url":"/em/3/"},"min_level":25},{"chance":5,"condition_values":[],"max_level":25,"method":{"name":"good-rod","url":"/em/3/"},"min_level":25}],"max_chance":65,"version":{"name":"x","url":"/v/23/"}},{"encounter_details":[{"chance":35,"condition_values":[],"max_level":35,"method":{"name":"super-rod","url":"/em/4/"},"min_level":35}],"max_chance":35,"version":{"name":"y","url":"/v/24/"}}]}]}